oida/__init__.py
oida/__main__.py
oida/checkers/__init__.py
oida/checkers/base.py
oida/checkers/components.py
oida/checkers/config.py
oida/checkers/django_orm.py
oida/checkers/imports.py
oida/commands/__init__.py
oida/commands/componentize.py
oida/commands/config.py
oida/commands/linter.py
oida/component.py
oida/config.py
oida/config_generator.py
oida/console.py
oida/discovery.py
oida/flake8.py
oida/module.py
oida/statistics/__init__.py
oida/statistics/statistics_generator.py
oida/utils.py
oida-0.2.2.dist-info/METADATA
oida-0.2.2.dist-info/WHEEL
oida-0.2.2.dist-info/entry_points.txt
oida-0.2.2.dist-info/licenses/LICENCE
oida-0.2.2.dist-info/RECORD
