Metadata-Version: 2.4
Name: oida
Version: 0.2.2
Summary: Oida is Oda's linter that enforces code style and modularization in our Django projects.
License: MIT
License-File: LICENCE
Author: Oda
Author-email: tech@oda.com
Requires-Python: >=3.10,<4.0
Classifier: Development Status :: 3 - Alpha
Classifier: Environment :: Console
Classifier: Framework :: Django
Classifier: Framework :: Flake8
Classifier: Intended Audience :: Developers
Classifier: License :: OSI Approved :: MIT License
Classifier: Programming Language :: Python
Classifier: Programming Language :: Python :: 3
Classifier: Programming Language :: Python :: 3.10
Classifier: Programming Language :: Python :: 3.11
Classifier: Programming Language :: Python :: 3.12
Classifier: Programming Language :: Python :: 3.13
Classifier: Programming Language :: Python :: 3.14
Classifier: Topic :: Software Development :: Libraries :: Python Modules
Classifier: Topic :: Software Development :: Quality Assurance
Requires-Dist: libcst (>=1.0.0,<2.0.0)
Requires-Dist: tomli (>=1.0.0) ; python_version < "3.11"
Project-URL: Homepage, https://github.com/kolonialno/oida
Project-URL: Repository, https://github.com/kolonialno/oida
